pytalog/spark/__init__.py
pytalog/spark/data_sources/__init__.py
pytalog/spark/data_sources/guarantee.py
pytalog/spark/data_sources/spark.py
pytalog_spark-0.1.1.dist-info/METADATA
pytalog_spark-0.1.1.dist-info/WHEEL
pytalog_spark-0.1.1.dist-info/top_level.txt
pytalog_spark-0.1.1.dist-info/RECORD
