Metadata-Version: 2.1
Name: pytalog-spark
Version: 0.1.1
Requires-Dist: pytalog-base==0.1.1
Requires-Dist: pyspark>=3.2.1
Provides-Extra: dev
Requires-Dist: pytalog-base==0.1.1; extra == "dev"
Requires-Dist: pyspark==3.2.1; extra == "dev"
Requires-Dist: pandas; extra == "dev"
Provides-Extra: strict
Requires-Dist: pytalog-base==0.1.1; extra == "strict"
Requires-Dist: pyspark==3.2.1; extra == "strict"
Provides-Extra: test
Requires-Dist: pytalog-base==0.1.1; extra == "test"
Requires-Dist: pyspark==3.2.1; extra == "test"
Requires-Dist: pandas; extra == "test"
